Workbook

Sheet Assumptions
A1: AI-enabled claims transformation: business case model
A2: Owner: Claims Finance · Version 0.9 (draft) · Synthetic demo data for a fictional insurer
A4: Assumption | B4: Value | C4: Unit | D4: Source / note
A5: Addressable claims cost (motor and home) | B5: 4500 | C5: A$m | D5: FY26 actuals
A6: Current leakage rate | B6: 0.06 | C6: % | D6: Management estimate; not validated by Internal Audit or Appointed Actuary
A7: Leakage reduction from AI | B7: 0.3 | C7: % | D7: Industry studies
A8: Realisation factor | B8: 0.68 | C8: % | D8: Management judgement
A9: Claims handling efficiency at full run rate | B9: 25 | C9: A$m p.a. | D9: Vendor estimate
A10: Discount rate | B10: 0.09 | C10: % | D10: Group hurdle rate
A11: Net insurance revenue FY26 (for COR impact) | B11: 9260 | C11: A$m | D11: Annual Report 2026, p7
A13: Full run-rate leakage benefit (A$m) | B13: =B5*B6*B7*B8 -> 55.08
A14: Full run-rate total benefit (A$m) | B14: =B13+B9 -> 80.08

Sheet Cash flows
A1: Cash flows (A$m)
A3: Line | B3: FY27 | C3: FY28 | D3: FY29 | E3: FY30 | F3: FY31 | G3: Total
A4: Platform implementation | B4: 18 | C4: 12 | D4: 6 | E4: 0 | F4: 0 | G4: =SUM(B4:F4) -> 36
A5: Data migration and integration | B5: 6 | C5: 6.5 | D5: 4 | E5: 0 | F5: 0 | G5: =SUM(B5:F5) -> 16.5
A6: Change management and training | B6: 4 | C6: 4 | D6: 3.5 | E6: 0 | F6: 0 | G6: =SUM(B6:F6) -> 11.5
A7: Contingency | B7: 2 | C7: 3.5 | D7: 2 | E7: 0 | F7: 0 | G7: =SUM(B7:F7) -> 7.5
A8: One-off investment | B8: =SUM(B4:B7) -> 30 | C8: =SUM(C4:C7) -> 26 | D8: =SUM(D4:D7) -> 15.5 | E8: =SUM(E4:E7) -> 0 | F8: =SUM(F4:F7) -> 0 | G8: =SUM(B8:F8) -> 71.5
A9: Run costs: licence and support | B9: 4 | C9: 9 | D9: 12 | E9: 12 | F9: 12 | G9: =SUM(B9:F9) -> 49
A11: Benefit ramp (% of full run rate) | B11: 0.1 | C11: 0.5 | D11: 0.9 | E11: 1 | F11: 1
A12: Benefits | B12: =Assumptions!$B$14*B11 -> 8.008 | C12: =Assumptions!$B$14*C11 -> 40.04 | D12: =Assumptions!$B$14*D11 -> 72.072 | E12: =Assumptions!$B$14*E11 -> 80.08 | F12: =Assumptions!$B$14*F11 -> 80.08 | G12: =SUM(B12:F12) -> 280.28
A14: Net cash flow | B14: =B12-B8-B9 -> -25.992 | C14: =C12-C8-C9 -> 5.04 | D14: =D12-D8-D9 -> 44.572 | E14: =E12-E8-E9 -> 68.08 | F14: =F12-F8-F9 -> 68.08 | G14: =SUM(B14:F14) -> 159.78
A15: Cumulative net cash flow | B15: =B14 -> -25.992 | C15: =C14+B15 -> -20.952 | D15: =D14+C15 -> 23.62 | E15: =E14+D15 -> 91.7 | F15: =F14+E15 -> 159.78
A16: Payback helper (years) | B16: =IF(B15>=0,0,0) -> 0 | C16: =IF(AND(B15<0,C15>=0),1+(-B15)/C14,0) -> 0 | D16: =IF(AND(C15<0,D15>=0),2+(-C15)/D14,0) -> 2.4700709 | E16: =IF(AND(D15<0,E15>=0),3+(-D15)/E14,0) -> 0 | F16: =IF(AND(E15<0,F15>=0),4+(-E15)/F14,0) -> 0
A18: Payback (years from start of FY27) | B18: =SUM(B16:F16) -> 2.4700709
A19: Payback (months) | B19: =B18*12 -> 29.640851
A20: NPV at discount rate, FY27–FY31 (A$m) | B20: =NPV(Assumptions!B10,B14:F14) -> 107.29087
A21: Total investment incl. contingency (A$m) | B21: =G8 -> 71.5
A22: COR improvement at full run rate (pts) | B22: =(Assumptions!B14-F9)/Assumptions!B11*100 -> 0.73520518
A25: Blue = inputs · black = formulas · yellow = key assumptions (Assumptions sheet).
